langchain_hyperbrowser/__init__.py
langchain_hyperbrowser/_utilities.py
langchain_hyperbrowser/browser_use_tool.py
langchain_hyperbrowser/claude_computer_use_tool.py
langchain_hyperbrowser/extract_tool.py
langchain_hyperbrowser/hyperbrowser_loader.py
langchain_hyperbrowser/openai_cua_tool.py
langchain_hyperbrowser-0.4.0.dist-info/LICENSE
langchain_hyperbrowser-0.4.0.dist-info/METADATA
langchain_hyperbrowser-0.4.0.dist-info/WHEEL
langchain_hyperbrowser-0.4.0.dist-info/RECORD
