Metadata-Version: 2.3
Name: langchain-hyperbrowser
Version: 0.4.0
Summary: An integration package connecting Hyperbrowser and LangChain
License: MIT
Requires-Python: >=3.9,<4.0
Classifier: License :: OSI Approved :: MIT License
Classifier: Programming Language :: Python :: 3
Classifier: Programming Language :: Python :: 3.9
Classifier: Programming Language :: Python :: 3.10
Classifier: Programming Language :: Python :: 3.11
Classifier: Programming Language :: Python :: 3.12
Classifier: Programming Language :: Python :: 3.13
Requires-Dist: hyperbrowser (>=0.39.0,<0.40.0)
Requires-Dist: langchain-core (>=0.3.15,<0.4.0)
Project-URL: Homepage, https://github.com/hyperbrowserai/langchain-hyperbrowser
Project-URL: Repository, https://github.com/hyperbrowserai/langchain-hyperbrowser
Project-URL: Source Code, https://github.com/hyperbrowserai/langchain-hyperbrowser
